youqu_imagecenter_rpc/__init__.py
youqu_imagecenter_rpc/__version__.py
youqu_imagecenter_rpc/conf.py
youqu_imagecenter_rpc/install_depends.py
youqu_imagecenter_rpc/server.py
youqu_imagecenter_rpc-2024.6.21.dist-info/METADATA
youqu_imagecenter_rpc-2024.6.21.dist-info/WHEEL
youqu_imagecenter_rpc-2024.6.21.dist-info/licenses/LICENSE
youqu_imagecenter_rpc-2024.6.21.dist-info/RECORD
